Lab2/docs/src/shift_right/src/shift_right.v
/* 32 - bit Right Shift register with shift_enable */
module shift_right 
#(
    parameter WIDTH = 32
)
(
    input clk,
    input rst_n,
    input [WIDTH - 1:0] data_in,
    input shift_enable,
    input load,
    output reg serial_out
);

    reg [WIDTH - 1:0] data_out;
    always @(posedge clk or negedge rst_n) begin
        if (!rst_n)
            {serial_out, data_out} <= {1'b0, {WIDTH-1{1'b0}}};
        else if(load)
            data_out <= data_in;
        else if (shift_enable)
            {data_out[WIDTH-1:0], serial_out} <= {1'b0, data_out[WIDTH-1:0]};
        else 
            data_out <= data_out;
    end

endmodule

Lab2/docs/src/shift_right/src/shift_right_tb.v
`timescale 1ns/100ps
`include "shift_right/src/shift_right.v"

module shift_right_tb;
    localparam WIDTH=32;

    reg clk;
    reg rst_n;
    reg [WIDTH-1:0] data_in;
    reg shift_en;
    reg load;
    wire serial_out;

    reg passed = 1;

    reg tst_out;
    reg [WIDTH-1:0] tst_temp;
    reg [WIDTH-1:0] tst_value = 32'hFF123456;

    shift_right #(.WIDTH(WIDTH)) shift_right_dut (
        .clk(clk),
        .load(load),
        .rst_n(rst_n),
        .data_in(data_in),
        .shift_enable(shift_en),
        .serial_out(serial_out)
    );

    /* Clock generation */
    initial begin
      clk = 0;
      forever #10 clk = ~clk;
    end

    task check;
        begin
            if(tst_out !== serial_out) begin
                $display("[T=%0g] Test failed: expected %g, got %g", $time, tst_out, serial_out);
                passed = 0;
            end 
        end
    endtask

    integer i;

    initial begin
        $dumpfile("build/shift_right.vcd");
        $dumpvars(1);
        $display("#################### Starting simulation ####################");
        
        shift_en = 0;
        rst_n = 1;
        load = 0;

        tst_temp = tst_value;

        @(negedge clk) begin
            data_in <= tst_value;
            load <= 1;
        end
        @(negedge clk) begin
            load <= 0;
        end
        shift_en <= 1;

        /* Test: Load value */
        $display("########## TEST: Load value ##########");
        for (i = 0; i < 32; i = i + 1) begin
            @(posedge clk)
                {tst_temp[WIDTH-1:0], tst_out} <= {1'b0, tst_temp[WIDTH-1:0]};
            @(negedge clk) check;
        end

        /* Test: Reset, Should Be 0 */
        $display("########## TEST: Reset ##########");
        rst_n = 0;
        tst_out = 0;
        @(posedge clk) check;
        rst_n = 1;

        /* Test: Buffer is empty */
        $display("########## TEST: Buffer is empty ##########");
        @(posedge clk) check;

        /* Test: Shift right continue */
        $display("########## TEST: Shift right continue ##########");
        @(negedge clk) begin
            tst_temp <= tst_value;
            data_in <= tst_value;
            load <= 1;
        end
        @(negedge clk) begin
            load <= 0;
        end
        shift_en <= 1;

        for (i = 0; i < 16; i = i + 1) begin
            @(posedge clk)
                {tst_temp[WIDTH-1:0], tst_out} <= {1'b0, tst_temp[WIDTH-1:0]};
            @(negedge clk) check;
        end
        if(passed)
            $display("[T=%0g] All tests passed", $time);
        else
            $display("[T=%0g] Some tests failed", $time);
        #10; $finish;
    end


endmodule

Lab2/src/shift_right/build/shift_right.vcd
$date
	Sun Apr  7 10:04:45 2024
$end
$version
	Icarus Verilog
$end
$timescale
	100ps
$end
$scope module shift_right_tb $end
$var wire 1 ! serial_out $end
$var parameter 32 " WIDTH $end
$var reg 1 # clk $end
$var reg 32 $ data_in [31:0] $end
$var reg 1 % load $end
$var reg 1 & passed $end
$var reg 1 ' rst_n $end
$var reg 1 ( shift_en $end
$var reg 1 ) tst_out $end
$var reg 32 * tst_temp [31:0] $end
$var reg 32 + tst_value [31:0] $end
$var integer 32 , i [31:0] $end
$upscope $end
$enddefinitions $end
$comment Show the parameter values. $end
$dumpall
b100000 "
$end
#0
$dumpvars
bx ,
b11111111000100100011010001010110 +
b11111111000100100011010001010110 *
x)
0(
1'
1&
0%
bx $
0#
x!
$end
#100
1#
#200
1%
b11111111000100100011010001010110 $
0#
#300
1#
#400
1(
0%
b0 ,
0#
#500
0!
b1111111100010010001101000101011 *
0)
1#
#600
b1 ,
0#
#700
1!
b111111110001001000110100010101 *
1)
1#
#800
b10 ,
0#
#900
b11111111000100100011010001010 *
1#
#1000
b11 ,
0#
#1100
0!
b1111111100010010001101000101 *
0)
1#
#1200
b100 ,
0#
#1300
1!
b111111110001001000110100010 *
1)
1#
#1400
b101 ,
0#
#1500
0!
b11111111000100100011010001 *
0)
1#
#1600
b110 ,
0#
#1700
1!
b1111111100010010001101000 *
1)
1#
#1800
b111 ,
0#
#1900
0!
b111111110001001000110100 *
0)
1#
#2000
b1000 ,
0#
#2100
b11111111000100100011010 *
1#
#2200
b1001 ,
0#
#2300
b1111111100010010001101 *
1#
#2400
b1010 ,
0#
#2500
1!
b111111110001001000110 *
1)
1#
#2600
b1011 ,
0#
#2700
0!
b11111111000100100011 *
0)
1#
#2800
b1100 ,
0#
#2900
1!
b1111111100010010001 *
1)
1#
#3000
b1101 ,
0#
#3100
b111111110001001000 *
1#
#3200
b1110 ,
0#
#3300
0!
b11111111000100100 *
0)
1#
#3400
b1111 ,
0#
#3500
b1111111100010010 *
1#
#3600
b10000 ,
0#
#3700
b111111110001001 *
1#
#3800
b10001 ,
0#
#3900
1!
b11111111000100 *
1)
1#
#4000
b10010 ,
0#
#4100
0!
b1111111100010 *
0)
1#
#4200
b10011 ,
0#
#4300
b111111110001 *
1#
#4400
b10100 ,
0#
#4500
1!
b11111111000 *
1)
1#
#4600
b10101 ,
0#
#4700
0!
b1111111100 *
0)
1#
#4800
b10110 ,
0#
#4900
b111111110 *
1#
#5000
b10111 ,
0#
#5100
b11111111 *
1#
#5200
b11000 ,
0#
#5300
1!
b1111111 *
1)
1#
#5400
b11001 ,
0#
#5500
b111111 *
1#
#5600
b11010 ,
0#
#5700
b11111 *
1#
#5800
b11011 ,
0#
#5900
b1111 *
1#
#6000
b11100 ,
0#
#6100
b111 *
1#
#6200
b11101 ,
0#
#6300
b11 *
1#
#6400
b11110 ,
0#
#6500
b1 *
1#
#6600
b11111 ,
0#
#6700
b0 *
1#
#6800
0!
0)
0'
b100000 ,
0#
#6900
1'
1#
#7000
0#
#7100
1#
#7200
1%
b11111111000100100011010001010110 *
0#
#7300
1#
#7400
0%
b0 ,
0#
#7500
b1111111100010010001101000101011 *
1#
#7600
b1 ,
0#
#7700
1!
b111111110001001000110100010101 *
1)
1#
#7800
b10 ,
0#
#7900
b11111111000100100011010001010 *
1#
#8000
b11 ,
0#
#8100
0!
b1111111100010010001101000101 *
0)
1#
#8200
b100 ,
0#
#8300
1!
b111111110001001000110100010 *
1)
1#
#8400
b101 ,
0#
#8500
0!
b11111111000100100011010001 *
0)
1#
#8600
b110 ,
0#
#8700
1!
b1111111100010010001101000 *
1)
1#
#8800
b111 ,
0#
#8900
0!
b111111110001001000110100 *
0)
1#
#9000
b1000 ,
0#
#9100
b11111111000100100011010 *
1#
#9200
b1001 ,
0#
#9300
b1111111100010010001101 *
1#
#9400
b1010 ,
0#
#9500
1!
b111111110001001000110 *
1)
1#
#9600
b1011 ,
0#
#9700
0!
b11111111000100100011 *
0)
1#
#9800
b1100 ,
0#
#9900
1!
b1111111100010010001 *
1)
1#
#10000
b1101 ,
0#
#10100
b111111110001001000 *
1#
#10200
b1110 ,
0#
#10300
0!
b11111111000100100 *
0)
1#
#10400
b1111 ,
0#
#10500
b1111111100010010 *
1#
#10600
b10000 ,
0#
