Lab2/src/fsm/src/sub.v
`timescale 1ps/1ps
module sub 
#(
    parameter WIDTH = 32
)
(
    input [WIDTH - 1:0] x, y,
    output [WIDTH - 1:0] z
);
    assign z = x + (~y) + 1;
  
endmodule

Lab2/src/fsm/src/mul2.v
`timescale 1ps/1ps
module mul2 
#(
    parameter WIDTH = 32
)
(
    input [WIDTH - 1:0] in,
    output [WIDTH - 1:0] out
);
    assign out = in << 1;
endmodule

Lab2/docs/src/fsm/src/adder.v
`timescale 1ps/1ps
module adder 
#(
    parameter WIDTH = 32
)
(
    input [WIDTH - 1:0] x, y,
    output [WIDTH - 1:0] z
);
    assign z = x + y;
endmodule

Lab2/docs/src/fsm/src/div2.v
`timescale 1ps/1ps
module div2 
#(
    parameter WIDTH = 32
)
(
    input [WIDTH - 1:0] in,
    output [WIDTH - 1:0] out
);
    assign out = in >> 1;
endmodule

Lab2/src/fsm/src/fsm.v
`include "fsm/src/sub.v"
`include "fsm/src/adder.v"
`include "fsm/src/mul2.v"
`include "fsm/src/div2.v"
module fsm 
#(
    parameter WIDTH = 32,
    parameter OP_WIDTH = WIDTH + 3
)
(
    input clk,
    input [WIDTH - 1:0] a, b,
    input rst_n,
    output reg[OP_WIDTH-1:0] out,
    output reg ready
);

    localparam [3:0]
        S0 = 4'b0000,
        S1 = 4'b0001,
        S2 = 4'b0010,
        S3 = 4'b0011,
        S4 = 4'b0100,
        S5 = 4'b0101,
        S6 = 4'b0110,
        S7 = 4'b0111;
    reg [3:0] state;

    /* registers to store intermediate results */
    reg[OP_WIDTH - 1:0] reg1, reg2, reg3, reg4;

    reg[1:0] mul_cnt = 0;

    /* instantiate div2 module */
    reg [OP_WIDTH - 1:0] div2_in;
    wire [OP_WIDTH - 1:0] div2_out;
    div2 #(.WIDTH(OP_WIDTH)) div2_inst (
        .in(div2_in),
        .out(div2_out)
    );

    /* instantiate adder module */
    reg [OP_WIDTH - 1:0] add_a, add_b;
    wire [OP_WIDTH - 1:0] add_z;
    adder #(.WIDTH(OP_WIDTH)) add_inst (
        .x(add_a),
        .y(add_b),
        .z(add_z)
    );

    /* instantiate mul2 module */
    reg [OP_WIDTH - 1:0] mul2_in;
    wire [OP_WIDTH - 1:0] mul2_out;
    mul2 #(.WIDTH(OP_WIDTH)) mul2_inst (
        .in(mul2_in),
        .out(mul2_out)
    );

    /* instantiate sub module */
    reg [OP_WIDTH - 1:0] sub_a, sub_b;
    wire [OP_WIDTH - 1:0] sub_z;
    sub #(.WIDTH(OP_WIDTH)) sub_inst (
        .x(sub_a),
        .y(sub_b),
        .z(sub_z)
    );

    always @(posedge clk, negedge rst_n) begin
        if (!rst_n) begin
            state <= S0;
            out <= {WIDTH + 4{1'b0}};
            ready <= 1'b0;
        end
        else begin
            case (state)
                S0: begin
                    if(!ready) begin
                        /* load A and B */
                        reg1 <= a;
                        reg2 <= b;
                        reg3 <= a;
                        reg4 <= b;
                        state <= S1;
                    end
                end
                S1: begin
                    /* reg1 = (A / 2) */
                    reg1 <= div2_out;
                    state <= S2;
                end
                S2: begin
                    /* reg1 = (A / 2 + B) */
                    reg1 <= add_z;
                    state <= S3;
                end
                S3: begin
                    /* reg4 = (B / 2) */
                    reg4 <= div2_out;
                    state <= S4;
                end
                S4: begin
                    /* reg3 = (A - B / 2)*/
                    reg3 <= sub_z;
                    state <= S5;
                end
                S5: begin
                    /* reg1 = ((A / 2) + B) * 8 */
                    if(mul_cnt !== 2'd2) begin
                        reg1 <= mul2_out;
                        mul_cnt <= mul_cnt + 1;
                        state <= S5;
                    end
                    else begin
                        mul_cnt <= 0;
                        reg1 <= mul2_out;
                        state <= S6;
                    end
                end
                S6: begin
                    /* reg3 = (A - B / 2) * 4 */
                    if (mul_cnt !== 2'd1) begin
                        reg3 <= mul2_out;
                        mul_cnt <= mul_cnt + 1;
                        state <= S6;
                    end
                    else begin
                        mul_cnt <= 0;
                        reg3 <= mul2_out;
                        state <= S7;
                    end
                end
                S7: begin
                    /* out = ((A / 2) + B) * 8 + (A - B / 2) * 4 */
                    out <= add_z;
                    state <= S0;
                    ready <= 1'b1;
                end
                default: 
                    state <= state;
            endcase
        end
    end

    /* Connect inputs of adder, mul2, sub and div2 */
    always@(*) begin
        case (state)
            S1: begin
                div2_in = reg1;
            end 
            S2: begin
                add_a = reg1;
                add_b = reg2;
            end
            S3: begin
                div2_in = reg4;
            end
            S4: begin
                sub_a = reg3;
                sub_b = reg4;
            end
            S5: begin
                mul2_in = reg1;
            end
            S6: begin
                mul2_in = reg3;
            end
            S7: begin
                add_a = reg1;
                add_b = reg3;
            end
            default: begin
                div2_in = 0;
                add_a = 0;
                add_b = 0;
                mul2_in = 0;
                sub_a = 0;
                sub_b = 0;
            end
        endcase
    end
endmodule

Lab2/src/fsm/src/fsm_tb.v
`timescale 1ps/1ps
`include "fsm/src/fsm.v"
module fsm_tb;
    localparam WIDTH = 32;
    localparam OP_WIDTH = WIDTH + 3;
    reg clk;
    reg [WIDTH - 1:0] a, b;
    reg rst_n;
    wire ready;
    wire [OP_WIDTH-1:0] out;
    reg passed = 1;
    reg [OP_WIDTH-1:0] tst_out;
    fsm #(.WIDTH(WIDTH)) fsm_dut (
        .clk(clk),
        .rst_n(rst_n),
        .a(a),
        .b(b),
        .out(out),
        .ready(ready)
    );

    /* Clock generation */
    initial begin
        clk = 0;
        forever #10 clk = ~clk;
    end

    task check;
        begin
            if(tst_out !== out) begin
                $display("[T=%0g] Test failed: expected %g, got %g", $time, tst_out, out);
                passed = 0;
            end 
        end
    endtask

    task calfunc(input [WIDTH - 1:0] a, b, output [OP_WIDTH-1:0] out);
        begin
            out = ((a / 2) + b) * 8 + (a - (b / 2)) * 4;
        end
    endtask

    initial begin
        $dumpfile("build/fsm.vcd");
        $dumpvars(1);

        $monitor("[T=%0d] state->%0d, reg1=%0d, reg2=%0d, reg3=%00d, reg4=%0d, mul_cnt=%0d, ready=%b, out=%0d", 
            $time, fsm_dut.state, fsm_dut.reg1, fsm_dut.reg2, fsm_dut.reg3, fsm_dut.reg4, fsm_dut.mul_cnt, fsm_dut.ready, fsm_dut.out);

        rst_n = 0;
        
        /* Test: a = 6 and b = 4 */
        $display("[T=%0g] Test 1: a = 6, b = 4", $time);
        @(negedge clk) begin
            a <= 32'd6;
            b <= 32'd4;
            rst_n <= 1;
        end
        while (!ready) begin
            @(posedge clk);
        end
        calfunc(a, b, tst_out);
        check;

        /* Test: Reset */
        $display("[T=%0g] Test 2: Reset", $time);
        @(negedge clk) begin
            rst_n <= 0;
            a <= 32'd1234;
            b <= 32'd5678;
        end
        tst_out = 0;
        @(posedge clk) check;

        @(negedge clk) begin
            rst_n <= 1;
        end

        while(!ready) begin
            @(posedge clk);
        end
        calfunc(a, b, tst_out);
        @(posedge clk) check;

        /* Test: Max values a = 2^32 - 1 and b = 2^32 - 1 */
        $display("[T=%0g] Test 3: a = 2^32 - 1, b = 2^32 - 1", $time);
        @(negedge clk) begin
            // a = 2^31 - 1
            a <= 32'h7FFFFFFF;
            // b = 2^31 - 1
            b <= 32'h7FFFFFFF;
            rst_n <= 1;
        end
        while (!ready) begin
            @(posedge clk);
        end
        calfunc(a, b, tst_out);
        @(posedge clk) check;

        /* Test: Zero values a = 0 and b = 0 */
        $display("[T=%0g] Test 4: a = 0, b = 0", $time);
        @(negedge clk) begin
            a <= 32'h0;
            b <= 32'h0;
            rst_n <= 0;
        end
        @(negedge clk) begin
            rst_n <= 1;
        end
        while (!ready) begin
            @(posedge clk);
        end
        calfunc(a, b, tst_out);
        @(posedge clk) check;

        /* Test: Min values a = -2^31 and b = -2^31 */
        $display("[T=%0g] Test 5: a = -2^31, b = -2^31", $time);
        @(negedge clk) begin
            // a = -2^31
            a <= 32'h80000000;
            // b = -2^31
            b <= 32'h80000000;
            rst_n <= 0;
        end
        @(negedge clk) begin
            rst_n <= 1;
        end
        while (!ready) begin
            @(posedge clk);
        end
        calfunc(a, b, tst_out);
        @(posedge clk) check;

        if(passed)
            $display("[T=%0g] All tests passed", $time);
        else
            $display("[T=%0g] Some tests failed", $time);
        #30; $finish;
    end  
    
endmodule

Lab2/src/fsm/build/fsm.vcd
$date
	Sun Apr  7 17:23:58 2024
$end
$version
	Icarus Verilog
$end
$timescale
	1ps
$end
$scope module fsm_tb $end
$var wire 1 ! ready $end
$var wire 35 " out [34:0] $end
$var parameter 33 # OP_WIDTH $end
$var parameter 32 $ WIDTH $end
$var reg 32 % a [31:0] $end
$var reg 32 & b [31:0] $end
$var reg 1 ' clk $end
$var reg 1 ( passed $end
$var reg 1 ) rst_n $end
$var reg 35 * tst_out [34:0] $end
$upscope $end
$enddefinitions $end
$comment Show the parameter values. $end
$dumpall
b100000 $
b100011 #
$end
#0
$dumpvars
bx *
0)
1(
0'
bx &
bx %
b0 "
0!
$end
#10
1'
#20
1)
b100 &
b110 %
0'
#30
1'
#40
0'
#50
1'
#60
0'
#70
1'
#80
0'
#90
1'
#100
0'
#110
1'
#120
0'
#130
1'
#140
0'
#150
1'
#160
0'
#170
1'
#180
0'
#190
1'
#200
0'
#210
1'
#220
0'
#230
1!
b1001000 "
1'
#240
0'
#250
b1001000 *
1'
#260
0!
b0 "
b1011000101110 &
b10011010010 %
0)
b0 *
0'
#270
1'
#280
1)
0'
#290
1'
#300
0'
#310
1'
#320
0'
#330
1'
#340
0'
#350
1'
#360
0'
#370
1'
#380
0'
#390
1'
#400
0'
#410
1'
#420
0'
#430
1'
#440
0'
#450
1'
#460
0'
#470
1'
#480
0'
#490
1!
b1010101110100100 "
1'
#500
0'
#510
b1010101110100100 *
1'
#520
0'
#530
1'
#540
b1111111111111111111111111111111 &
b1111111111111111111111111111111 %
0'
#550
1'
#560
0!
b0 "
0)
b0 &
b0 %
0'
#570
1'
#580
1)
0'
#590
1'
#600
0'
#610
1'
#620
0'
#630
1'
#640
0'
#650
1'
#660
0'
#670
1'
#680
0'
#690
1'
#700
0'
#710
1'
#720
0'
#730
1'
#740
0'
#750
1'
#760
0'
#770
1'
#780
0'
#790
1!
1'
#800
0'
#810
b0 *
1'
#820
0'
#830
1'
#840
0!
0)
b10000000000000000000000000000000 &
b10000000000000000000000000000000 %
0'
#850
1'
#860
1)
0'
#870
1'
#880
0'
#890
1'
#900
0'
#910
1'
#920
0'
#930
1'
#940
0'
#950
1'
#960
0'
#970
1'
#980
0'
#990
1'
#1000
0'
#1010
1'
#1020
0'
#1030
1'
#1040
0'
#1050
1'
#1060
0'
#1070
1!
b11100000000000000000000000000000000 "
1'
#1080
0'
#1090
b11100000000000000000000000000000000 *
1'
