Lab2/docs/src/freq_div/src/freq_div.v
/* Frequency clock divider */
module freq_div 
#(
    parameter DIV_CNT = 10,
    parameter WIDTH = $clog2(DIV_CNT)
)
(
    input clk_in,
    input rst_n,
    input enable,
    output clk_out
);
    reg [WIDTH-1:0] cnt;

    always @(posedge clk_in or negedge rst_n) begin
        if(!rst_n)
            cnt <= {WIDTH{1'b0}};
        else if (enable)
            if (cnt == DIV_CNT - 1)
                cnt <= {WIDTH{1'b0}};
            else 
                cnt <= cnt + 1'b1;
        else 
            cnt <= cnt;
    end

    assign clk_out = (cnt == 0 && rst_n && enable) ? 1'b1 : 1'b0;
endmodule

Lab2/docs/src/freq_div/src/freq_div_tb.v
`timescale 1ns/1ps
`include "freq_div/src/freq_div.v"

module freq_div_tb;
    localparam DIV_CNT = 10;
    reg  clk_in;
    reg  rst_n;
    reg enable;
    wire clk_out;
    freq_div #(.DIV_CNT(DIV_CNT)) fd_dut(
        .clk_in (clk_in),
        .rst_n (rst_n),
        .enable (enable),
        .clk_out (clk_out)
    );

    reg passed = 1;
    reg tst_out;

    /* Clock generation */

    initial begin
        clk_in = 0;
        forever #10 clk_in = !clk_in;
    end

    task check;
        begin
            if(tst_out != clk_out) begin
                $display("[T=%0g] Test failed: expected %g, got %g", $time, tst_out, clk_out);
                passed = 1'b0;
            end
        end
    endtask

    integer i;
    initial begin
        $dumpfile("build/freq_div.vcd");
        $dumpvars(1);
        $monitor("[T=%0d] enable=%b, rst_n=%b, cnt=%0d, clk_out=%b", $time, enable, rst_n, fd_dut.cnt, clk_out);

        
        rst_n = 0;
        enable = 1;
        #1 rst_n = 1;

        tst_out = 1'b0;

        /* Test 1: Count test */
        $display("[T=%0g] Test 1: Count test", $time);
        for(i = 1; i < 98; i = i + 1) begin
            @(posedge clk_in) begin
                if(i % DIV_CNT == 0)
                    tst_out = 1'b1;
                else tst_out = 1'b0;
            end
            @(negedge clk_in) begin
                check;
            end
        end

        /* Test 2: Reset, Should Be 0 */
        $display("[T=%0g] Test 2: Reset, Should Be 0", $time);
        @(posedge clk_in) begin
            rst_n <= 0;
            tst_out <= 0;
        end
        @(negedge clk_in) check;

        #1 rst_n = 1;

        /* Test 3: Continue count */
        $display("[T=%0g] Test 3: Continue count", $time);
        for(i = 1; i < 98; i = i + 1) begin
            @(posedge clk_in) begin
                if(i % DIV_CNT == 0)
                    tst_out = 1'b1;
                else tst_out = 1'b0;
            end
            @(negedge clk_in) begin
                check;
            end
        end

        /* Test 4: Enable disable */
        $display("[T=%0g] Test 4: Enable disable", $time);
        rst_n = 0;
        enable <= 0;
        @(posedge clk_in) begin
            tst_out <= 0;
            rst_n <= 1;
        end
        repeat(93) @(negedge clk_in) check;

        if(passed)
            $display("[T=%0g] All tests passed", $time);
        else
            $display("[T=%0g] Some tests failed", $time);
        #30; $finish;

    end
endmodule

Lab2/docs/src/freq_div/build/freq_div.vcd
$date
	Sun Apr  7 20:05:12 2024
$end
$version
	Icarus Verilog
$end
$timescale
	1ps
$end
$scope module freq_div_tb $end
$var wire 1 ! clk_out $end
$var parameter 32 " DIV_CNT $end
$var reg 1 # clk_in $end
$var reg 1 $ enable $end
$var reg 1 % passed $end
$var reg 1 & rst_n $end
$var reg 1 ' tst_out $end
$var integer 32 ( i [31:0] $end
$upscope $end
$enddefinitions $end
$comment Show the parameter values. $end
$dumpall
b1010 "
$end
#0
$dumpvars
bx (
x'
0&
1%
1$
0#
0!
$end
#1000
1!
b1 (
0'
1&
#10000
0!
1#
#20000
b10 (
0#
#30000
1#
#40000
b11 (
0#
#50000
1#
#60000
b100 (
0#
#70000
1#
#80000
b101 (
0#
#90000
1#
#100000
b110 (
0#
#110000
1#
#120000
b111 (
0#
#130000
1#
#140000
b1000 (
0#
#150000
1#
#160000
b1001 (
0#
#170000
1#
#180000
b1010 (
0#
#190000
1!
1'
1#
#200000
b1011 (
0#
#210000
0!
0'
1#
#220000
b1100 (
0#
#230000
1#
#240000
b1101 (
0#
#250000
1#
#260000
b1110 (
0#
#270000
1#
#280000
b1111 (
0#
#290000
1#
#300000
b10000 (
0#
#310000
1#
#320000
b10001 (
0#
#330000
1#
#340000
b10010 (
0#
#350000
1#
#360000
b10011 (
0#
#370000
1#
#380000
b10100 (
0#
#390000
1!
1'
1#
#400000
b10101 (
0#
#410000
0!
0'
1#
#420000
b10110 (
0#
#430000
1#
#440000
b10111 (
0#
#450000
1#
#460000
b11000 (
0#
#470000
1#
#480000
b11001 (
0#
#490000
1#
#500000
b11010 (
0#
#510000
1#
#520000
b11011 (
0#
#530000
1#
#540000
b11100 (
0#
#550000
1#
#560000
b11101 (
0#
#570000
1#
#580000
b11110 (
0#
#590000
1!
1'
1#
#600000
b11111 (
0#
#610000
0!
0'
1#
#620000
b100000 (
0#
#630000
1#
#640000
b100001 (
0#
#650000
1#
#660000
b100010 (
0#
#670000
1#
#680000
b100011 (
0#
#690000
1#
#700000
b100100 (
0#
#710000
1#
#720000
b100101 (
0#
#730000
1#
#740000
b100110 (
0#
#750000
1#
#760000
b100111 (
0#
#770000
1#
#780000
b101000 (
0#
#790000
1!
1'
1#
#800000
b101001 (
0#
#810000
0!
0'
1#
#820000
b101010 (
0#
#830000
1#
#840000
b101011 (
0#
#850000
1#
#860000
b101100 (
0#
#870000
1#
#880000
b101101 (
0#
#890000
1#
#900000
b101110 (
0#
#910000
1#
#920000
b101111 (
0#
#930000
1#
#940000
b110000 (
0#
#950000
1#
#960000
b110001 (
0#
#970000
1#
#980000
b110010 (
0#
#990000
1!
1'
1#
#1000000
b110011 (
0#
#1010000
0!
0'
1#
#1020000
b110100 (
0#
#1030000
1#
#1040000
b110101 (
0#
#1050000
1#
#1060000
b110110 (
0#
#1070000
1#
#1080000
b110111 (
0#
#1090000
1#
#1100000
b111000 (
0#
#1110000
1#
#1120000
b111001 (
0#
#1130000
1#
#1140000
b111010 (
0#
#1150000
1#
#1160000
b111011 (
0#
#1170000
1#
#1180000
b111100 (
0#
#1190000
1!
1'
1#
#1200000
b111101 (
0#
#1210000
0!
0'
1#
#1220000
b111110 (
0#
#1230000
1#
#1240000
b111111 (
0#
#1250000
1#
#1260000
b1000000 (
0#
#1270000
1#
#1280000
b1000001 (
0#
#1290000
1#
#1300000
b1000010 (
0#
#1310000
1#
#1320000
b1000011 (
0#
#1330000
1#
#1340000
b1000100 (
0#
#1350000
1#
#1360000
b1000101 (
0#
#1370000
1#
#1380000
b1000110 (
0#
#1390000
1!
1'
1#
#1400000
b1000111 (
0#
#1410000
0!
0'
1#
#1420000
b1001000 (
0#
#1430000
1#
#1440000
b1001001 (
0#
#1450000
1#
#1460000
b1001010 (
0#
#1470000
1#
#1480000
b1001011 (
0#
#1490000
1#
#1500000
b1001100 (
0#
#1510000
1#
#1520000
b1001101 (
0#
#1530000
1#
#1540000
b1001110 (
0#
#1550000
1#
#1560000
b1001111 (
0#
#1570000
1#
#1580000
b1010000 (
0#
#1590000
1!
1'
1#
#1600000
b1010001 (
0#
#1610000
0!
0'
1#
#1620000
b1010010 (
0#
#1630000
1#
#1640000
b1010011 (
0#
#1650000
1#
#1660000
b1010100 (
0#
#1670000
1#
#1680000
b1010101 (
0#
#1690000
1#
#1700000
b1010110 (
0#
#1710000
1#
#1720000
b1010111 (
0#
#1730000
1#
#1740000
b1011000 (
0#
#1750000
1#
#1760000
b1011001 (
0#
#1770000
1#
#1780000
b1011010 (
0#
#1790000
1!
1'
1#
#1800000
b1011011 (
0#
#1810000
0!
0'
1#
#1820000
b1011100 (
0#
#1830000
1#
#1840000
b1011101 (
0#
#1850000
1#
#1860000
b1011110 (
0#
#1870000
1#
#1880000
b1011111 (
0#
#1890000
1#
#1900000
b1100000 (
0#
#1910000
1#
#1920000
b1100001 (
0#
#1930000
1#
#1940000
b1100010 (
0#
#1950000
0&
1#
#1960000
0#
#1961000
1!
b1 (
1&
#1970000
0!
1#
#1980000
b10 (
0#
#1990000
1#
#2000000
b11 (
0#
#2010000
1#
#2020000
b100 (
0#
#2030000
1#
#2040000
b101 (
0#
#2050000
1#
#2060000
b110 (
0#
#2070000
1#
#2080000
b111 (
0#
#2090000
1#
#2100000
b1000 (
0#
#2110000
1#
#2120000
b1001 (
0#
#2130000
1#
#2140000
b1010 (
0#
#2150000
1!
1'
1#
#2160000
b1011 (
0#
#2170000
0!
0'
1#
#2180000
b1100 (
0#
#2190000
1#
#2200000
b1101 (
0#
#2210000
1#
#2220000
b1110 (
0#
#2230000
1#
#2240000
b1111 (
0#
#2250000
1#
#2260000
b10000 (
0#
#2270000
1#
#2280000
b10001 (
0#
#2290000
1#
#2300000
b10010 (
0#
#2310000
1#
#2320000
b10011 (
0#
#2330000
1#
#2340000
b10100 (
0#
#2350000
1!
1'
1#
#2360000
b10101 (
0#
#2370000
0!
0'
1#
#2380000
b10110 (
0#
#2390000
1#
#2400000
b10111 (
0#
#2410000
1#
#2420000
b11000 (
0#
#2430000
1#
#2440000
b11001 (
0#
#2450000
1#
#2460000
b11010 (
0#
#2470000
1#
#2480000
b11011 (
0#
#2490000
1#
#2500000
b11100 (
0#
#2510000
1#
#2520000
b11101 (
0#
#2530000
1#
#2540000
b11110 (
0#
#2550000
1!
1'
1#
#2560000
b11111 (
0#
#2570000
0!
0'
1#
#2580000
b100000 (
0#
#2590000
1#
#2600000
b100001 (
0#
#2610000
1#
#2620000
b100010 (
0#
#2630000
1#
#2640000
b100011 (
0#
#2650000
1#
#2660000
b100100 (
0#
#2670000
1#
#2680000
b100101 (
0#
#2690000
1#
#2700000
b100110 (
0#
#2710000
1#
#2720000
b100111 (
0#
#2730000
1#
#2740000
b101000 (
0#
#2750000
1!
1'
1#
#2760000
b101001 (
0#
#2770000
0!
0'
1#
#2780000
b101010 (
0#
#2790000
1#
#2800000
b101011 (
0#
#2810000
1#
#2820000
b101100 (
0#
#2830000
1#
#2840000
b101101 (
0#
#2850000
1#
#2860000
b101110 (
0#
#2870000
1#
#2880000
b101111 (
0#
#2890000
1#
#2900000
b110000 (
0#
#2910000
1#
#2920000
b110001 (
0#
#2930000
1#
#2940000
b110010 (
0#
#2950000
1!
1'
1#
#2960000
b110011 (
0#
#2970000
0!
0'
1#
#2980000
b110100 (
0#
#2990000
1#
#3000000
b110101 (
0#
#3010000
1#
#3020000
b110110 (
0#
#3030000
1#
#3040000
b110111 (
0#
#3050000
1#
#3060000
b111000 (
0#
#3070000
1#
#3080000
b111001 (
0#
#3090000
1#
#3100000
b111010 (
0#
#3110000
1#
#3120000
b111011 (
0#
#3130000
1#
#3140000
b111100 (
0#
#3150000
1!
1'
1#
#3160000
b111101 (
0#
#3170000
0!
0'
1#
#3180000
b111110 (
0#
#3190000
1#
#3200000
b111111 (
0#
#3210000
1#
#3220000
b1000000 (
0#
#3230000
1#
#3240000
b1000001 (
0#
#3250000
1#
#3260000
b1000010 (
0#
#3270000
1#
#3280000
b1000011 (
0#
#3290000
1#
#3300000
b1000100 (
0#
#3310000
1#
#3320000
b1000101 (
0#
#3330000
1#
#3340000
b1000110 (
0#
#3350000
1!
1'
1#
#3360000
b1000111 (
0#
#3370000
0!
0'
1#
#3380000
b1001000 (
0#
#3390000
1#
#3400000
b1001001 (
0#
#3410000
1#
#3420000
b1001010 (
0#
#3430000
1#
#3440000
b1001011 (
0#
#3450000
1#
#3460000
b1001100 (
0#
#3470000
1#
#3480000
b1001101 (
0#
#3490000
1#
#3500000
b1001110 (
0#
#3510000
1#
#3520000
b1001111 (
0#
#3530000
1#
#3540000
b1010000 (
0#
#3550000
1!
1'
1#
#3560000
b1010001 (
0#
#3570000
0!
0'
1#
#3580000
b1010010 (
0#
#3590000
1#
#3600000
b1010011 (
0#
#3610000
1#
#3620000
b1010100 (
0#
#3630000
1#
#3640000
b1010101 (
0#
#3650000
1#
#3660000
b1010110 (
0#
#3670000
1#
#3680000
b1010111 (
0#
#3690000
1#
#3700000
b1011000 (
0#
#3710000
1#
#3720000
b1011001 (
0#
#3730000
1#
#3740000
b1011010 (
0#
#3750000
1!
1'
1#
#3760000
b1011011 (
0#
#3770000
0!
0'
1#
#3780000
b1011100 (
0#
#3790000
1#
#3800000
b1011101 (
0#
#3810000
1#
#3820000
b1011110 (
0#
#3830000
1#
#3840000
b1011111 (
0#
#3850000
1#
#3860000
b1100000 (
0#
#3870000
1#
#3880000
b1100001 (
0#
#3890000
1#
#3900000
0$
0&
b1100010 (
0#
#3910000
1&
1#
